ffmpeg/__init__.py
ffmpeg/ffmpeg.py
ffmpeg/exception/__init__.py
ffmpeg/exception/exceptions.py
ffmpeg/expressions/__init__.py
ffmpeg/expressions/math.py
ffmpeg/ffplay/__init__.py
ffmpeg/ffplay/ffplay.py
ffmpeg/ffprobe/__init__.py
ffmpeg/ffprobe/ffprobe.py
ffmpeg/filters/__init__.py
ffmpeg/filters/adelay.py
ffmpeg/filters/aformat.py
ffmpeg/filters/amix.py
ffmpeg/filters/apply_filter.py
ffmpeg/filters/base.py
ffmpeg/filters/concat.py
ffmpeg/filters/crop.py
ffmpeg/filters/delogo.py
ffmpeg/filters/draw_box.py
ffmpeg/filters/draw_text.py
ffmpeg/filters/format.py
ffmpeg/filters/hstack.py
ffmpeg/filters/overlay.py
ffmpeg/filters/sar.py
ffmpeg/filters/scale.py
ffmpeg/filters/split.py
ffmpeg/filters/subtitles.py
ffmpeg/filters/timebase.py
ffmpeg/filters/volume.py
ffmpeg/filters/vstack.py
ffmpeg/filters/xfade.py
ffmpeg/filters/mixins/__init__.py
ffmpeg/filters/mixins/enable.py
ffmpeg/inputs/__init__.py
ffmpeg/inputs/audio.py
ffmpeg/inputs/base_input.py
ffmpeg/inputs/base_virtual_input.py
ffmpeg/inputs/file_input.py
ffmpeg/inputs/image.py
ffmpeg/inputs/streams.py
ffmpeg/inputs/video.py
ffmpeg/inputs/virtual_video.py
ffmpeg/inputs/options/__init__.py
ffmpeg/inputs/options/base_options.py
ffmpeg/inputs/options/file_input_option.py
ffmpeg/output/__init__.py
ffmpeg/output/output.py
ffmpeg/utils/__init__.py
ffmpeg/utils/commons.py
ffmpeg/utils/diagram.py
ffmpeg_studio-0.1.2.dist-info/licenses/LICENSE
ffmpeg_studio-0.1.2.dist-info/WHEEL
ffmpeg_studio-0.1.2.dist-info/METADATA
ffmpeg_studio-0.1.2.dist-info/RECORD
