Metadata-Version: 2.4
Name: ffmpeg-studio
Version: 0.1.2
Summary: FFmpeg Wrapper for Python
Keywords: ffmpeg,media,video processing,audio,python,wrapper,transcoding
Author: Aman Raza
Requires-Python: >=3.11
License-Expression: GPL-3.0-or-later
Classifier: Intended Audience :: Developers
Classifier: Natural Language :: English
Classifier: Topic :: Multimedia
Classifier: Topic :: Multimedia :: Sound/Audio
Classifier: Topic :: Multimedia :: Sound/Audio :: Analysis
Classifier: Topic :: Multimedia :: Video
Classifier: Topic :: Multimedia :: Video :: Capture
Classifier: Topic :: Multimedia :: Video :: Conversion
Classifier: Programming Language :: Python :: 3
Classifier: Programming Language :: Python :: 3.11
Classifier: Operating System :: OS Independent
License-File: LICENSE
Requires-Dist: mkdocs ; extra == "dev"
Requires-Dist: mkdocs-material ; extra == "dev"
Requires-Dist: pymdown-extensions ; extra == "dev"
Requires-Dist: mkdocstrings[python] ; extra == "dev"
Requires-Dist: mkdocs-autorefs ; extra == "dev"
Project-URL: Documentation, https://electro199.github.io/ffmpeg-studio/
Project-URL: Homepage, https://github.com/electro199/ffmpeg-studio
Project-URL: Repository, https://github.com/electro199/ffmpeg-studio
Provides-Extra: dev
